
<EDKSYSTEM ARCH="spartan3e" EDKVERSION="9.1" PART="xc3s500efg320-4" SRC="F:/zRabG/Xlnx/UPR2007/P4_edg_dbg/system.xmp" TIMESTAMP="Thu Oct 11 20:35:28 2007&#xA;">

  <MODULES>
    <MODULE DOC_DRIVER="f:/EDK/sw/XilinxProcessorIPLib/drivers/cpu_v1_01_a/doc/html/api/index.html" DOC_IP="f:/EDK/hw/XilinxProcessorIPLib/pcores/microblaze_v6_00_a/doc/microblaze.pdf" HWVERSION="6.00.a" INSTANCE="microblaze_0" IPTYPE="PROCESSOR" IS_PLACED="TRUE" MODCLASS="PROCESSOR" MODTYPE="microblaze">
      <DESCRIPTION TYPE="SHORT">MicroBlaze</DESCRIPTION>
      <DESCRIPTION TYPE="LONG">The MicroBlaze 32 bit soft processor</DESCRIPTION>
      <PARAMETER NAME="C_SCO" VALUE="0"/>
      <PARAMETER NAME="C_DATA_SIZE" VALUE="32"/>
      <PARAMETER NAME="C_DYNAMIC_BUS_SIZING" VALUE="1"/>
      <PARAMETER NAME="C_FAMILY" VALUE="virtex2"/>
      <PARAMETER NAME="C_INSTANCE" VALUE="microblaze"/>
      <PARAMETER CHANGEDBY="USER" NAME="C_AREA_OPTIMIZED" VALUE="1"/>
      <PARAMETER NAME="C_D_OPB" VALUE="1"/>
      <PARAMETER NAME="C_D_LMB" VALUE="1"/>
      <PARAMETER NAME="C_I_OPB" VALUE="1"/>
      <PARAMETER NAME="C_I_LMB" VALUE="1"/>
      <PARAMETER NAME="C_USE_MSR_INSTR" VALUE="1"/>
      <PARAMETER NAME="C_USE_PCMP_INSTR" VALUE="1"/>
      <PARAMETER NAME="C_USE_BARREL" VALUE="0"/>
      <PARAMETER NAME="C_USE_DIV" VALUE="0"/>
      <PARAMETER NAME="C_USE_HW_MUL" VALUE="1"/>
      <PARAMETER NAME="C_USE_FPU" VALUE="0"/>
      <PARAMETER NAME="C_UNALIGNED_EXCEPTIONS" VALUE="0"/>
      <PARAMETER NAME="C_ILL_OPCODE_EXCEPTION" VALUE="0"/>
      <PARAMETER NAME="C_IOPB_BUS_EXCEPTION" VALUE="0"/>
      <PARAMETER NAME="C_DOPB_BUS_EXCEPTION" VALUE="0"/>
      <PARAMETER NAME="C_DIV_ZERO_EXCEPTION" VALUE="0"/>
      <PARAMETER NAME="C_FPU_EXCEPTION" VALUE="0"/>
      <PARAMETER NAME="C_PVR" VALUE="0"/>
      <PARAMETER NAME="C_PVR_USER1" VALUE="0x00"/>
      <PARAMETER NAME="C_PVR_USER2" VALUE="0x00000000"/>
      <PARAMETER NAME="C_DEBUG_ENABLED" VALUE="0"/>
      <PARAMETER NAME="C_NUMBER_OF_PC_BRK" VALUE="1"/>
      <PARAMETER NAME="C_NUMBER_OF_RD_ADDR_BRK" VALUE="0"/>
      <PARAMETER NAME="C_NUMBER_OF_WR_ADDR_BRK" VALUE="0"/>
      <PARAMETER NAME="C_INTERRUPT_IS_EDGE" VALUE="0"/>
      <PARAMETER NAME="C_EDGE_IS_POSITIVE" VALUE="1"/>
      <PARAMETER NAME="C_RESET_MSR" VALUE="0x00000000"/>
      <PARAMETER NAME="C_OPCODE_0x0_ILLEGAL" VALUE="0"/>
      <PARAMETER NAME="C_FSL_LINKS" VALUE="0"/>
      <PARAMETER NAME="C_FSL_DATA_SIZE" VALUE="32"/>
      <PARAMETER NAME="C_ICACHE_BASEADDR" VALUE="0x00000000"/>
      <PARAMETER NAME="C_ICACHE_HIGHADDR" VALUE="0x3FFFFFFF"/>
      <PARAMETER NAME="C_USE_ICACHE" VALUE="0"/>
      <PARAMETER NAME="C_ALLOW_ICACHE_WR" VALUE="1"/>
      <PARAMETER NAME="C_ADDR_TAG_BITS" VALUE="17"/>
      <PARAMETER NAME="C_CACHE_BYTE_SIZE" VALUE="8192"/>
      <PARAMETER NAME="C_ICACHE_USE_FSL" VALUE="1"/>
      <PARAMETER NAME="C_ICACHE_LINE_LEN" VALUE="4"/>
      <PARAMETER NAME="C_DCACHE_BASEADDR" VALUE="0x00000000"/>
      <PARAMETER NAME="C_DCACHE_HIGHADDR" VALUE="0x3FFFFFFF"/>
      <PARAMETER NAME="C_USE_DCACHE" VALUE="0"/>
      <PARAMETER NAME="C_ALLOW_DCACHE_WR" VALUE="1"/>
      <PARAMETER NAME="C_DCACHE_ADDR_TAG" VALUE="17"/>
      <PARAMETER NAME="C_DCACHE_BYTE_SIZE" VALUE="8192"/>
      <PARAMETER NAME="C_DCACHE_USE_FSL" VALUE="1"/>
      <PARAMETER NAME="C_DCACHE_LINE_LEN" VALUE="4"/>
      <BUSINTERFACE BIFRANK="MASTER" BIF_X="0" BIF_Y="0" BUSNAME="dlmb" BUSSTD="LMB" NAME="DLMB" ORIENTED="WEST"/>
      <BUSINTERFACE BIFRANK="MASTER" BIF_X="1" BIF_Y="0" BUSNAME="ilmb" BUSSTD="LMB" NAME="ILMB" ORIENTED="EAST"/>
      <BUSINTERFACE BIFRANK="MASTER" BIF_X="0" BIF_Y="1" BUSNAME="mb_opb" BUSSTD="OPB" NAME="DOPB" ORIENTED="WEST"/>
      <BUSINTERFACE BIFRANK="MASTER" BIF_X="1" BIF_Y="1" BUSNAME="mb_opb" BUSSTD="OPB" NAME="IOPB" ORIENTED="EAST"/>
      <PORT DIR="I" NAME="CLK" SIGIS="CLK" SIGNAME="__DEF__"/>
      <PORT DIR="I" NAME="RESET" SIGNAME="__DEF__"/>
      <PORT DIR="I" NAME="INTERRUPT" SIGIS="INTERRUPT" SIGNAME="__NOC__"/>
      <PORT DIR="I" NAME="DEBUG_RST" SIGNAME="__DEF__"/>
      <PORT DIR="I" NAME="EXT_BRK" SIGNAME="__DEF__"/>
      <PORT DIR="I" NAME="EXT_NM_BRK" SIGNAME="__DEF__"/>
      <PORT DIR="I" NAME="DBG_STOP" SIGNAME="__NOC__"/>
      <PORT DIR="O" NAME="MB_Halted" SIGNAME="__NOC__"/>
      <PORT DIR="I" NAME="INSTR" SIGNAME="__DEF__"/>
      <PORT DIR="O" NAME="I_ADDRTAG" SIGNAME="__DEF__"/>
      <PORT DIR="I" NAME="IREADY" SIGNAME="__DEF__"/>
      <PORT DIR="I" NAME="IWAIT" SIGNAME="__DEF__"/>
      <PORT DIR="O" NAME="INSTR_ADDR" SIGNAME="__DEF__"/>
      <PORT DIR="O" NAME="IFETCH" SIGNAME="__DEF__"/>
      <PORT DIR="O" NAME="I_AS" SIGNAME="__DEF__"/>
      <PORT DIR="I" NAME="DATA_READ" SIGNAME="__DEF__"/>
      <PORT DIR="I" NAME="DREADY" SIGNAME="__DEF__"/>
      <PORT DIR="I" NAME="DWAIT" SIGNAME="__DEF__"/>
      <PORT DIR="O" NAME="DATA_WRITE" SIGNAME="__DEF__"/>
      <PORT DIR="O" NAME="DATA_ADDR" SIGNAME="__DEF__"/>
      <PORT DIR="O" NAME="D_ADDRTAG" SIGNAME="__DEF__"/>
      <PORT DIR="O" NAME="D_AS" SIGNAME="__DEF__"/>
      <PORT DIR="O" NAME="READ_STROBE" SIGNAME="__DEF__"/>
      <PORT DIR="O" NAME="WRITE_STROBE" SIGNAME="__DEF__"/>
      <PORT DIR="O" NAME="BYTE_ENABLE" SIGNAME="__DEF__"/>
      <PORT DIR="O" NAME="DM_ABUS" SIGNAME="__DEF__"/>
      <PORT DIR="O" NAME="DM_BE" SIGNAME="__DEF__"/>
      <PORT DIR="O" NAME="DM_BUSLOCK" SIGNAME="__DEF__"/>
      <PORT DIR="O" NAME="DM_DBUS" SIGNAME="__DEF__"/>
      <PORT DIR="O" NAME="DM_REQUEST" SIGNAME="__DEF__"/>
      <PORT DIR="O" NAME="DM_RNW" SIGNAME="__DEF__"/>
      <PORT DIR="O" NAME="DM_SELECT" SIGNAME="__DEF__"/>
      <PORT DIR="O" NAME="DM_SEQADDR" SIGNAME="__DEF__"/>
      <PORT DIR="I" NAME="DOPB_DBUS" SIGNAME="__DEF__"/>
      <PORT DIR="I" NAME="DOPB_ERRACK" SIGNAME="__DEF__"/>
      <PORT DIR="I" NAME="DOPB_MGRANT" SIGNAME="__DEF__"/>
      <PORT DIR="I" NAME="DOPB_RETRY" SIGNAME="__DEF__"/>
      <PORT DIR="I" NAME="DOPB_TIMEOUT" SIGNAME="__DEF__"/>
      <PORT DIR="I" NAME="DOPB_XFERACK" SIGNAME="__DEF__"/>
      <PORT DIR="O" NAME="IM_ABUS" SIGNAME="__DEF__"/>
      <PORT DIR="O" NAME="IM_BE" SIGNAME="__DEF__"/>
      <PORT DIR="O" NAME="IM_BUSLOCK" SIGNAME="__DEF__"/>
      <PORT DIR="O" NAME="IM_DBUS" SIGNAME="__DEF__"/>
      <PORT DIR="O" NAME="IM_REQUEST" SIGNAME="__DEF__"/>
      <PORT DIR="O" NAME="IM_RNW" SIGNAME="__DEF__"/>
      <PORT DIR="O" NAME="IM_SELECT" SIGNAME="__DEF__"/>
      <PORT DIR="O" NAME="IM_SEQADDR" SIGNAME="__DEF__"/>
      <PORT DIR="I" NAME="IOPB_DBUS" SIGNAME="__DEF__"/>
      <PORT DIR="I" NAME="IOPB_ERRACK" SIGNAME="__DEF__"/>
      <PORT DIR="I" NAME="IOPB_MGRANT" SIGNAME="__DEF__"/>
      <PORT DIR="I" NAME="IOPB_RETRY" SIGNAME="__DEF__"/>
      <PORT DIR="I" NAME="IOPB_TIMEOUT" SIGNAME="__DEF__"/>
      <PORT DIR="I" NAME="IOPB_XFERACK" SIGNAME="__DEF__"/>
      <PORT DIR="I" NAME="DBG_CLK" SIGNAME="__DEF__"/>
      <PORT DIR="I" NAME="DBG_TDI" SIGNAME="__DEF__"/>
      <PORT DIR="O" NAME="DBG_TDO" SIGNAME="__DEF__"/>
      <PORT DIR="I" NAME="DBG_REG_EN" SIGNAME="__DEF__"/>
      <PORT DIR="I" NAME="DBG_CAPTURE" SIGNAME="__DEF__"/>
      <PORT DIR="I" NAME="DBG_UPDATE" SIGNAME="__DEF__"/>
      <PORT DIR="O" NAME="Trace_Instruction" SIGNAME="__DEF__"/>
      <PORT DIR="O" NAME="Trace_Valid_Instr" SIGNAME="__DEF__"/>
      <PORT DIR="O" NAME="Trace_PC" SIGNAME="__DEF__"/>
      <PORT DIR="O" NAME="Trace_Reg_Write" SIGNAME="__DEF__"/>
      <PORT DIR="O" NAME="Trace_Reg_Addr" SIGNAME="__DEF__"/>
      <PORT DIR="O" NAME="Trace_MSR_Reg" SIGNAME="__DEF__"/>
      <PORT DIR="O" NAME="Trace_New_Reg_Value" SIGNAME="__DEF__"/>
      <PORT DIR="O" NAME="Trace_Exception_Taken" SIGNAME="__DEF__"/>
      <PORT DIR="O" NAME="Trace_Exception_Kind" SIGNAME="__DEF__"/>
      <PORT DIR="O" NAME="Trace_Jump_Taken" SIGNAME="__DEF__"/>
      <PORT DIR="O" NAME="Trace_Delay_Slot" SIGNAME="__DEF__"/>
      <PORT DIR="O" NAME="Trace_Data_Address" SIGNAME="__DEF__"/>
      <PORT DIR="O" NAME="Trace_Data_Access" SIGNAME="__DEF__"/>
      <PORT DIR="O" NAME="Trace_Data_Read" SIGNAME="__DEF__"/>
      <PORT DIR="O" NAME="Trace_Data_Write" SIGNAME="__DEF__"/>
      <PORT DIR="O" NAME="Trace_Data_Write_Value" SIGNAME="__DEF__"/>
      <PORT DIR="O" NAME="Trace_Data_Byte_Enable" SIGNAME="__DEF__"/>
      <PORT DIR="O" NAME="Trace_DCache_Req" SIGNAME="__DEF__"/>
      <PORT DIR="O" NAME="Trace_DCache_Hit" SIGNAME="__DEF__"/>
      <PORT DIR="O" NAME="Trace_ICache_Req" SIGNAME="__DEF__"/>
      <PORT DIR="O" NAME="Trace_ICache_Hit" SIGNAME="__DEF__"/>
      <PORT DIR="O" NAME="Trace_OF_PipeRun" SIGNAME="__DEF__"/>
      <PORT DIR="O" NAME="Trace_EX_PipeRun" SIGNAME="__DEF__"/>
      <PORT DIR="O" NAME="Trace_MEM_PipeRun" SIGNAME="__DEF__"/>
      <PORT DIR="O" NAME="FSL0_S_CLK" SIGIS="CLK" SIGNAME="__DEF__"/>
      <PORT DIR="O" NAME="FSL0_S_READ" SIGNAME="__DEF__"/>
      <PORT DIR="I" NAME="FSL0_S_DATA" SIGNAME="__DEF__"/>
      <PORT DIR="I" NAME="FSL0_S_CONTROL" SIGNAME="__DEF__"/>
      <PORT DIR="I" NAME="FSL0_S_EXISTS" SIGNAME="__DEF__"/>
      <PORT DIR="O" NAME="FSL0_M_CLK" SIGIS="CLK" SIGNAME="__DEF__"/>
      <PORT DIR="O" NAME="FSL0_M_WRITE" SIGNAME="__DEF__"/>
      <PORT DIR="O" NAME="FSL0_M_DATA" SIGNAME="__DEF__"/>
      <PORT DIR="O" NAME="FSL0_M_CONTROL" SIGNAME="__DEF__"/>
      <PORT DIR="I" NAME="FSL0_M_FULL" SIGNAME="__DEF__"/>
      <PORT DIR="O" NAME="FSL1_S_CLK" SIGIS="CLK" SIGNAME="__DEF__"/>
      <PORT DIR="O" NAME="FSL1_S_READ" SIGNAME="__DEF__"/>
      <PORT DIR="I" NAME="FSL1_S_DATA" SIGNAME="__DEF__"/>
      <PORT DIR="I" NAME="FSL1_S_CONTROL" SIGNAME="__DEF__"/>
      <PORT DIR="I" NAME="FSL1_S_EXISTS" SIGNAME="__DEF__"/>
      <PORT DIR="O" NAME="FSL1_M_CLK" SIGIS="CLK" SIGNAME="__DEF__"/>
      <PORT DIR="O" NAME="FSL1_M_WRITE" SIGNAME="__DEF__"/>
      <PORT DIR="O" NAME="FSL1_M_DATA" SIGNAME="__DEF__"/>
      <PORT DIR="O" NAME="FSL1_M_CONTROL" SIGNAME="__DEF__"/>
      <PORT DIR="I" NAME="FSL1_M_FULL" SIGNAME="__DEF__"/>
      <PORT DIR="O" NAME="FSL2_S_CLK" SIGIS="CLK" SIGNAME="__DEF__"/>
      <PORT DIR="O" NAME="FSL2_S_READ" SIGNAME="__DEF__"/>
      <PORT DIR="I" NAME="FSL2_S_DATA" SIGNAME="__DEF__"/>
      <PORT DIR="I" NAME="FSL2_S_CONTROL" SIGNAME="__DEF__"/>
      <PORT DIR="I" NAME="FSL2_S_EXISTS" SIGNAME="__DEF__"/>
      <PORT DIR="O" NAME="FSL2_M_CLK" SIGIS="CLK" SIGNAME="__DEF__"/>
      <PORT DIR="O" NAME="FSL2_M_WRITE" SIGNAME="__DEF__"/>
      <PORT DIR="O" NAME="FSL2_M_DATA" SIGNAME="__DEF__"/>
      <PORT DIR="O" NAME="FSL2_M_CONTROL" SIGNAME="__DEF__"/>
      <PORT DIR="I" NAME="FSL2_M_FULL" SIGNAME="__DEF__"/>
      <PORT DIR="O" NAME="FSL3_S_CLK" SIGIS="CLK" SIGNAME="__DEF__"/>
      <PORT DIR="O" NAME="FSL3_S_READ" SIGNAME="__DEF__"/>
      <PORT DIR="I" NAME="FSL3_S_DATA" SIGNAME="__DEF__"/>
      <PORT DIR="I" NAME="FSL3_S_CONTROL" SIGNAME="__DEF__"/>
      <PORT DIR="I" NAME="FSL3_S_EXISTS" SIGNAME="__DEF__"/>
      <PORT DIR="O" NAME="FSL3_M_CLK" SIGIS="CLK" SIGNAME="__DEF__"/>
      <PORT DIR="O" NAME="FSL3_M_WRITE" SIGNAME="__DEF__"/>
      <PORT DIR="O" NAME="FSL3_M_DATA" SIGNAME="__DEF__"/>
      <PORT DIR="O" NAME="FSL3_M_CONTROL" SIGNAME="__DEF__"/>
      <PORT DIR="I" NAME="FSL3_M_FULL" SIGNAME="__DEF__"/>
      <PORT DIR="O" NAME="FSL4_S_CLK" SIGIS="CLK" SIGNAME="__DEF__"/>
      <PORT DIR="O" NAME="FSL4_S_READ" SIGNAME="__DEF__"/>
      <PORT DIR="I" NAME="FSL4_S_DATA" SIGNAME="__DEF__"/>
      <PORT DIR="I" NAME="FSL4_S_CONTROL" SIGNAME="__DEF__"/>
      <PORT DIR="I" NAME="FSL4_S_EXISTS" SIGNAME="__DEF__"/>
      <PORT DIR="O" NAME="FSL4_M_CLK" SIGIS="CLK" SIGNAME="__DEF__"/>
      <PORT DIR="O" NAME="FSL4_M_WRITE" SIGNAME="__DEF__"/>
      <PORT DIR="O" NAME="FSL4_M_DATA" SIGNAME="__DEF__"/>
      <PORT DIR="O" NAME="FSL4_M_CONTROL" SIGNAME="__DEF__"/>
      <PORT DIR="I" NAME="FSL4_M_FULL" SIGNAME="__DEF__"/>
      <PORT DIR="O" NAME="FSL5_S_CLK" SIGIS="CLK" SIGNAME="__DEF__"/>
      <PORT DIR="O" NAME="FSL5_S_READ" SIGNAME="__DEF__"/>
      <PORT DIR="I" NAME="FSL5_S_DATA" SIGNAME="__DEF__"/>
      <PORT DIR="I" NAME="FSL5_S_CONTROL" SIGNAME="__DEF__"/>
      <PORT DIR="I" NAME="FSL5_S_EXISTS" SIGNAME="__DEF__"/>
      <PORT DIR="O" NAME="FSL5_M_CLK" SIGIS="CLK" SIGNAME="__DEF__"/>
      <PORT DIR="O" NAME="FSL5_M_WRITE" SIGNAME="__DEF__"/>
      <PORT DIR="O" NAME="FSL5_M_DATA" SIGNAME="__DEF__"/>
      <PORT DIR="O" NAME="FSL5_M_CONTROL" SIGNAME="__DEF__"/>
      <PORT DIR="I" NAME="FSL5_M_FULL" SIGNAME="__DEF__"/>
      <PORT DIR="O" NAME="FSL6_S_CLK" SIGIS="CLK" SIGNAME="__DEF__"/>
      <PORT DIR="O" NAME="FSL6_S_READ" SIGNAME="__DEF__"/>
      <PORT DIR="I" NAME="FSL6_S_DATA" SIGNAME="__DEF__"/>
      <PORT DIR="I" NAME="FSL6_S_CONTROL" SIGNAME="__DEF__"/>
      <PORT DIR="I" NAME="FSL6_S_EXISTS" SIGNAME="__DEF__"/>
      <PORT DIR="O" NAME="FSL6_M_CLK" SIGIS="CLK" SIGNAME="__DEF__"/>
      <PORT DIR="O" NAME="FSL6_M_WRITE" SIGNAME="__DEF__"/>
      <PORT DIR="O" NAME="FSL6_M_DATA" SIGNAME="__DEF__"/>
      <PORT DIR="O" NAME="FSL6_M_CONTROL" SIGNAME="__DEF__"/>
      <PORT DIR="I" NAME="FSL6_M_FULL" SIGNAME="__DEF__"/>
      <PORT DIR="O" NAME="FSL7_S_CLK" SIGIS="CLK" SIGNAME="__DEF__"/>
      <PORT DIR="O" NAME="FSL7_S_READ" SIGNAME="__DEF__"/>
      <PORT DIR="I" NAME="FSL7_S_DATA" SIGNAME="__DEF__"/>
      <PORT DIR="I" NAME="FSL7_S_CONTROL" SIGNAME="__DEF__"/>
      <PORT DIR="I" NAME="FSL7_S_EXISTS" SIGNAME="__DEF__"/>
      <PORT DIR="O" NAME="FSL7_M_CLK" SIGIS="CLK" SIGNAME="__DEF__"/>
      <PORT DIR="O" NAME="FSL7_M_WRITE" SIGNAME="__DEF__"/>
      <PORT DIR="O" NAME="FSL7_M_DATA" SIGNAME="__DEF__"/>
      <PORT DIR="O" NAME="FSL7_M_CONTROL" SIGNAME="__DEF__"/>
      <PORT DIR="I" NAME="FSL7_M_FULL" SIGNAME="__DEF__"/>
      <PORT DIR="O" NAME="ICACHE_FSL_IN_CLK" SIGIS="CLK" SIGNAME="__DEF__"/>
      <PORT DIR="O" NAME="ICACHE_FSL_IN_READ" SIGNAME="__DEF__"/>
      <PORT DIR="I" NAME="ICACHE_FSL_IN_DATA" SIGNAME="__DEF__"/>
      <PORT DIR="I" NAME="ICACHE_FSL_IN_CONTROL" SIGNAME="__DEF__"/>
      <PORT DIR="I" NAME="ICACHE_FSL_IN_EXISTS" SIGNAME="__DEF__"/>
      <PORT DIR="O" NAME="ICACHE_FSL_OUT_CLK" SIGIS="CLK" SIGNAME="__DEF__"/>
      <PORT DIR="O" NAME="ICACHE_FSL_OUT_WRITE" SIGNAME="__DEF__"/>
      <PORT DIR="O" NAME="ICACHE_FSL_OUT_DATA" SIGNAME="__DEF__"/>
      <PORT DIR="O" NAME="ICACHE_FSL_OUT_CONTROL" SIGNAME="__DEF__"/>
      <PORT DIR="I" NAME="ICACHE_FSL_OUT_FULL" SIGNAME="__DEF__"/>
      <PORT DIR="O" NAME="DCACHE_FSL_IN_CLK" SIGIS="CLK" SIGNAME="__DEF__"/>
      <PORT DIR="O" NAME="DCACHE_FSL_IN_READ" SIGNAME="__DEF__"/>
      <PORT DIR="I" NAME="DCACHE_FSL_IN_DATA" SIGNAME="__DEF__"/>
      <PORT DIR="I" NAME="DCACHE_FSL_IN_CONTROL" SIGNAME="__DEF__"/>
      <PORT DIR="I" NAME="DCACHE_FSL_IN_EXISTS" SIGNAME="__DEF__"/>
      <PORT DIR="O" NAME="DCACHE_FSL_OUT_CLK" SIGIS="CLK" SIGNAME="__DEF__"/>
      <PORT DIR="O" NAME="DCACHE_FSL_OUT_WRITE" SIGNAME="__DEF__"/>
      <PORT DIR="O" NAME="DCACHE_FSL_OUT_DATA" SIGNAME="__DEF__"/>
      <PORT DIR="O" NAME="DCACHE_FSL_OUT_CONTROL" SIGNAME="__DEF__"/>
      <PORT DIR="I" NAME="DCACHE_FSL_OUT_FULL" SIGNAME="__DEF__"/>
      <BUSINTERFACE BIFRANK="SLAVE" BUSNAME="__NOC__" BUSSTD="FSL" NAME="SFSL0"/>
      <BUSINTERFACE BIFRANK="MASTER" BUSNAME="__NOC__" BUSSTD="FSL" NAME="MFSL0"/>
      <BUSINTERFACE BIFRANK="SLAVE" BUSNAME="__NOC__" BUSSTD="FSL" NAME="SFSL1"/>
      <BUSINTERFACE BIFRANK="MASTER" BUSNAME="__NOC__" BUSSTD="FSL" NAME="MFSL1"/>
      <BUSINTERFACE BIFRANK="SLAVE" BUSNAME="__NOC__" BUSSTD="FSL" NAME="SFSL2"/>
      <BUSINTERFACE BIFRANK="MASTER" BUSNAME="__NOC__" BUSSTD="FSL" NAME="MFSL2"/>
      <BUSINTERFACE BIFRANK="SLAVE" BUSNAME="__NOC__" BUSSTD="FSL" NAME="SFSL3"/>
      <BUSINTERFACE BIFRANK="MASTER" BUSNAME="__NOC__" BUSSTD="FSL" NAME="MFSL3"/>
      <BUSINTERFACE BIFRANK="SLAVE" BUSNAME="__NOC__" BUSSTD="FSL" NAME="SFSL4"/>
      <BUSINTERFACE BIFRANK="MASTER" BUSNAME="__NOC__" BUSSTD="FSL" NAME="MFSL4"/>
      <BUSINTERFACE BIFRANK="SLAVE" BUSNAME="__NOC__" BUSSTD="FSL" NAME="SFSL5"/>
      <BUSINTERFACE BIFRANK="MASTER" BUSNAME="__NOC__" BUSSTD="FSL" NAME="MFSL5"/>
      <BUSINTERFACE BIFRANK="SLAVE" BUSNAME="__NOC__" BUSSTD="FSL" NAME="SFSL6"/>
      <BUSINTERFACE BIFRANK="MASTER" BUSNAME="__NOC__" BUSSTD="FSL" NAME="MFSL6"/>
      <BUSINTERFACE BIFRANK="SLAVE" BUSNAME="__NOC__" BUSSTD="FSL" NAME="SFSL7"/>
      <BUSINTERFACE BIFRANK="MASTER" BUSNAME="__NOC__" BUSSTD="FSL" NAME="MFSL7"/>
      <BUSINTERFACE BIFRANK="SLAVE" BUSNAME="__NOC__" BUSSTD="FSL" NAME="ICACHE_FSL_IN"/>
      <BUSINTERFACE BIFRANK="MASTER" BUSNAME="__NOC__" BUSSTD="FSL" NAME="ICACHE_FSL_OUT"/>
      <BUSINTERFACE BIFRANK="SLAVE" BUSNAME="__NOC__" BUSSTD="FSL" NAME="DCACHE_FSL_IN"/>
      <BUSINTERFACE BIFRANK="MASTER" BUSNAME="__NOC__" BUSSTD="FSL" NAME="DCACHE_FSL_OUT"/>
      <BUSINTERFACE BIFRANK="INITIATOR" BUSNAME="__NOC__" BUSSTD="XIL" NAME="IXCL"/>
      <BUSINTERFACE BIFRANK="INITIATOR" BUSNAME="__NOC__" BUSSTD="XIL" NAME="DXCL"/>
      <BUSINTERFACE BIFRANK="TARGET" BUSNAME="__NOC__" BUSSTD="XIL" NAME="DEBUG"/>
      <BUSINTERFACE BIFRANK="INITIATOR" BUSNAME="__NOC__" BUSSTD="XIL" NAME="TRACE"/>
    </MODULE>
    <MODULE BUSSTD="LMB" DOC_IP="f:/EDK/hw/XilinxProcessorIPLib/pcores/lmb_v10_v1_00_a/doc/lmb_v10.pdf" HWVERSION="1.00.a" INSTANCE="ilmb" IPTYPE="BUS" IS_PLACED="TRUE" MODCLASS="BUS" MODTYPE="lmb_v10">
      <DESCRIPTION TYPE="SHORT">Local Memory Bus (LMB) 1.0</DESCRIPTION>
      <DESCRIPTION TYPE="LONG">'The LMB is a fast, local bus for connecting MicroBlaze I and D ports to peripherals and BRAM'</DESCRIPTION>
      <PARAMETER NAME="C_LMB_NUM_SLAVES" VALUE="4"/>
      <PARAMETER NAME="C_LMB_AWIDTH" VALUE="32"/>
      <PARAMETER NAME="C_LMB_DWIDTH" VALUE="32"/>
      <PARAMETER NAME="C_EXT_RESET_HIGH" VALUE="1"/>
      <PORT DIR="I" INMHS="TRUE" NAME="SYS_Rst" SIGNAME="sys_rst_s"/>
      <PORT DIR="I" INMHS="TRUE" NAME="LMB_Clk" SIGIS="CLK" SIGNAME="sys_clk_s"/>
      <PORT DIR="O" NAME="LMB_Rst" SIGNAME="__DEF__"/>
      <PORT DIR="I" NAME="M_ABus" SIGNAME="__DEF__"/>
      <PORT DIR="I" NAME="M_ReadStrobe" SIGNAME="__DEF__"/>
      <PORT DIR="I" NAME="M_WriteStrobe" SIGNAME="__DEF__"/>
      <PORT DIR="I" NAME="M_AddrStrobe" SIGNAME="__DEF__"/>
      <PORT DIR="I" NAME="M_DBus" SIGNAME="__DEF__"/>
      <PORT DIR="I" NAME="M_BE" SIGNAME="__DEF__"/>
      <PORT DIR="I" NAME="Sl_DBus" SIGNAME="__DEF__"/>
      <PORT DIR="I" NAME="Sl_Ready" SIGNAME="__DEF__"/>
      <PORT DIR="O" NAME="LMB_ABus" SIGNAME="__DEF__"/>
      <PORT DIR="O" NAME="LMB_ReadStrobe" SIGNAME="__DEF__"/>
      <PORT DIR="O" NAME="LMB_WriteStrobe" SIGNAME="__DEF__"/>
      <PORT DIR="O" NAME="LMB_AddrStrobe" SIGNAME="__DEF__"/>
      <PORT DIR="O" NAME="LMB_ReadDBus" SIGNAME="__DEF__"/>
      <PORT DIR="O" NAME="LMB_WriteDBus" SIGNAME="__DEF__"/>
      <PORT DIR="O" NAME="LMB_Ready" SIGNAME="__DEF__"/>
      <PORT DIR="O" NAME="LMB_BE" SIGNAME="__DEF__"/>
    </MODULE>
    <MODULE BUSSTD="LMB" DOC_IP="f:/EDK/hw/XilinxProcessorIPLib/pcores/lmb_v10_v1_00_a/doc/lmb_v10.pdf" HWVERSION="1.00.a" INSTANCE="dlmb" IPTYPE="BUS" IS_PLACED="TRUE" MODCLASS="BUS" MODTYPE="lmb_v10">
      <DESCRIPTION TYPE="SHORT">Local Memory Bus (LMB) 1.0</DESCRIPTION>
      <DESCRIPTION TYPE="LONG">'The LMB is a fast, local bus for connecting MicroBlaze I and D ports to peripherals and BRAM'</DESCRIPTION>
      <PARAMETER NAME="C_LMB_NUM_SLAVES" VALUE="4"/>
      <PARAMETER NAME="C_LMB_AWIDTH" VALUE="32"/>
      <PARAMETER NAME="C_LMB_DWIDTH" VALUE="32"/>
      <PARAMETER NAME="C_EXT_RESET_HIGH" VALUE="1"/>
      <PORT DIR="I" INMHS="TRUE" NAME="SYS_Rst" SIGNAME="sys_rst_s"/>
      <PORT DIR="I" INMHS="TRUE" NAME="LMB_Clk" SIGIS="CLK" SIGNAME="sys_clk_s"/>
      <PORT DIR="O" NAME="LMB_Rst" SIGNAME="__DEF__"/>
      <PORT DIR="I" NAME="M_ABus" SIGNAME="__DEF__"/>
      <PORT DIR="I" NAME="M_ReadStrobe" SIGNAME="__DEF__"/>
      <PORT DIR="I" NAME="M_WriteStrobe" SIGNAME="__DEF__"/>
      <PORT DIR="I" NAME="M_AddrStrobe" SIGNAME="__DEF__"/>
      <PORT DIR="I" NAME="M_DBus" SIGNAME="__DEF__"/>
      <PORT DIR="I" NAME="M_BE" SIGNAME="__DEF__"/>
      <PORT DIR="I" NAME="Sl_DBus" SIGNAME="__DEF__"/>
      <PORT DIR="I" NAME="Sl_Ready" SIGNAME="__DEF__"/>
      <PORT DIR="O" NAME="LMB_ABus" SIGNAME="__DEF__"/>
      <PORT DIR="O" NAME="LMB_ReadStrobe" SIGNAME="__DEF__"/>
      <PORT DIR="O" NAME="LMB_WriteStrobe" SIGNAME="__DEF__"/>
      <PORT DIR="O" NAME="LMB_AddrStrobe" SIGNAME="__DEF__"/>
      <PORT DIR="O" NAME="LMB_ReadDBus" SIGNAME="__DEF__"/>
      <PORT DIR="O" NAME="LMB_WriteDBus" SIGNAME="__DEF__"/>
      <PORT DIR="O" NAME="LMB_Ready" SIGNAME="__DEF__"/>
      <PORT DIR="O" NAME="LMB_BE" SIGNAME="__DEF__"/>
    </MODULE>
    <MODULE DOC_DRIVER="f:/EDK/sw/XilinxProcessorIPLib/drivers/bram_v1_00_a/doc/html/api/index.html" DOC_IP="f:/EDK/hw/XilinxProcessorIPLib/pcores/lmb_bram_if_cntlr_v2_00_a/doc/lmb_bram_if_cntlr.pdf" HWVERSION="2.00.a" INSTANCE="dlmb_cntlr" IPTYPE="PERIPHERAL" IS_PLACED="TRUE" MODCLASS="MEMORY_CNTLR" MODTYPE="lmb_bram_if_cntlr">
      <DESCRIPTION TYPE="SHORT">LMB BRAM Controller</DESCRIPTION>
      <DESCRIPTION TYPE="LONG">Local Memory Bus (LMB) Block RAM (BRAM) Interface Controller connects to an lmb bus</DESCRIPTION>
      <PARAMETER CHANGEDBY="USER" NAME="C_BASEADDR" VALUE="0x00000000"/>
      <PARAMETER CHANGEDBY="USER" NAME="C_HIGHADDR" VALUE="0x00003fff"/>
      <PARAMETER NAME="C_MASK" VALUE="0x00800000"/>
      <PARAMETER NAME="C_LMB_AWIDTH" VALUE="32"/>
      <PARAMETER NAME="C_LMB_DWIDTH" VALUE="32"/>
      <BUSINTERFACE BIFRANK="SLAVE" BIF_X="0" BIF_Y="0" BUSNAME="dlmb" BUSSTD="LMB" NAME="SLMB"/>
      <BUSINTERFACE BIFRANK="INITIATOR" BIF_X="1" BIF_Y="0" BUSNAME="dlmb_port" BUSSTD="XIL" IS_INTCONN="TRUE" NAME="BRAM_PORT"/>
      <PORT DIR="I" NAME="LMB_Clk" SIGIS="CLK" SIGNAME="__DEF__"/>
      <PORT DIR="I" NAME="LMB_Rst" SIGNAME="__DEF__"/>
      <PORT DIR="I" NAME="LMB_ABus" SIGNAME="__DEF__"/>
      <PORT DIR="I" NAME="LMB_WriteDBus" SIGNAME="__DEF__"/>
      <PORT DIR="I" NAME="LMB_AddrStrobe" SIGNAME="__DEF__"/>
      <PORT DIR="I" NAME="LMB_ReadStrobe" SIGNAME="__DEF__"/>
      <PORT DIR="I" NAME="LMB_WriteStrobe" SIGNAME="__DEF__"/>
      <PORT DIR="I" NAME="LMB_BE" SIGNAME="__DEF__"/>
      <PORT DIR="O" NAME="Sl_DBus" SIGNAME="__DEF__"/>
      <PORT DIR="O" NAME="Sl_Ready" SIGNAME="__DEF__"/>
      <PORT DIR="O" NAME="BRAM_Rst_A" SIGNAME="__DEF__"/>
      <PORT DIR="O" NAME="BRAM_Clk_A" SIGNAME="__DEF__"/>
      <PORT DIR="O" NAME="BRAM_EN_A" SIGNAME="__DEF__"/>
      <PORT DIR="O" NAME="BRAM_WEN_A" SIGNAME="__DEF__"/>
      <PORT DIR="O" NAME="BRAM_Addr_A" SIGNAME="__DEF__"/>
      <PORT DIR="I" NAME="BRAM_Din_A" SIGNAME="__DEF__"/>
      <PORT DIR="O" NAME="BRAM_Dout_A" SIGNAME="__DEF__"/>
    </MODULE>
    <MODULE DOC_DRIVER="f:/EDK/sw/XilinxProcessorIPLib/drivers/bram_v1_00_a/doc/html/api/index.html" DOC_IP="f:/EDK/hw/XilinxProcessorIPLib/pcores/lmb_bram_if_cntlr_v2_00_a/doc/lmb_bram_if_cntlr.pdf" HWVERSION="2.00.a" INSTANCE="ilmb_cntlr" IPTYPE="PERIPHERAL" IS_PLACED="TRUE" MODCLASS="MEMORY_CNTLR" MODTYPE="lmb_bram_if_cntlr">
      <DESCRIPTION TYPE="SHORT">LMB BRAM Controller</DESCRIPTION>
      <DESCRIPTION TYPE="LONG">Local Memory Bus (LMB) Block RAM (BRAM) Interface Controller connects to an lmb bus</DESCRIPTION>
      <PARAMETER CHANGEDBY="USER" NAME="C_BASEADDR" VALUE="0x00000000"/>
      <PARAMETER CHANGEDBY="USER" NAME="C_HIGHADDR" VALUE="0x00003fff"/>
      <PARAMETER NAME="C_MASK" VALUE="0x00800000"/>
      <PARAMETER NAME="C_LMB_AWIDTH" VALUE="32"/>
      <PARAMETER NAME="C_LMB_DWIDTH" VALUE="32"/>
      <BUSINTERFACE BIFRANK="SLAVE" BIF_X="1" BIF_Y="0" BUSNAME="ilmb" BUSSTD="LMB" NAME="SLMB"/>
      <BUSINTERFACE BIFRANK="INITIATOR" BIF_X="0" BIF_Y="0" BUSNAME="ilmb_port" BUSSTD="XIL" IS_INTCONN="TRUE" NAME="BRAM_PORT"/>
      <PORT DIR="I" NAME="LMB_Clk" SIGIS="CLK" SIGNAME="__DEF__"/>
      <PORT DIR="I" NAME="LMB_Rst" SIGNAME="__DEF__"/>
      <PORT DIR="I" NAME="LMB_ABus" SIGNAME="__DEF__"/>
      <PORT DIR="I" NAME="LMB_WriteDBus" SIGNAME="__DEF__"/>
      <PORT DIR="I" NAME="LMB_AddrStrobe" SIGNAME="__DEF__"/>
      <PORT DIR="I" NAME="LMB_ReadStrobe" SIGNAME="__DEF__"/>
      <PORT DIR="I" NAME="LMB_WriteStrobe" SIGNAME="__DEF__"/>
      <PORT DIR="I" NAME="LMB_BE" SIGNAME="__DEF__"/>
      <PORT DIR="O" NAME="Sl_DBus" SIGNAME="__DEF__"/>
      <PORT DIR="O" NAME="Sl_Ready" SIGNAME="__DEF__"/>
      <PORT DIR="O" NAME="BRAM_Rst_A" SIGNAME="__DEF__"/>
      <PORT DIR="O" NAME="BRAM_Clk_A" SIGNAME="__DEF__"/>
      <PORT DIR="O" NAME="BRAM_EN_A" SIGNAME="__DEF__"/>
      <PORT DIR="O" NAME="BRAM_WEN_A" SIGNAME="__DEF__"/>
      <PORT DIR="O" NAME="BRAM_Addr_A" SIGNAME="__DEF__"/>
      <PORT DIR="I" NAME="BRAM_Din_A" SIGNAME="__DEF__"/>
      <PORT DIR="O" NAME="BRAM_Dout_A" SIGNAME="__DEF__"/>
    </MODULE>
    <MODULE DOC_DRIVER="f:/EDK/sw/XilinxProcessorIPLib/drivers/generic_v1_00_a/doc/html/api/index.html" DOC_IP="f:/EDK/hw/XilinxProcessorIPLib/pcores/bram_block_v1_00_a/doc/bram_block.pdf" HWVERSION="1.00.a" INSTANCE="lmb_bram" IPTYPE="PERIPHERAL" IS_PLACED="TRUE" MODCLASS="MEMORY" MODTYPE="bram_block">
      <DESCRIPTION TYPE="SHORT">Block RAM (BRAM) Block</DESCRIPTION>
      <DESCRIPTION TYPE="LONG">The BRAM Block is a configurable memory module that attaches to a variety of BRAM Interface Controllers.</DESCRIPTION>
      <PARAMETER NAME="C_MEMSIZE" VALUE="2048"/>
      <PARAMETER NAME="C_PORT_DWIDTH" VALUE="32"/>
      <PARAMETER NAME="C_PORT_AWIDTH" VALUE="32"/>
      <PARAMETER NAME="C_NUM_WE" VALUE="4"/>
      <PARAMETER NAME="C_FAMILY" VALUE="virtex2"/>
      <BUSINTERFACE BIFRANK="TARGET" BIF_X="1" BIF_Y="0" BUSNAME="ilmb_port" BUSSTD="XIL" IS_INTCONN="TRUE" NAME="PORTA"/>
      <BUSINTERFACE BIFRANK="TARGET" BIF_X="0" BIF_Y="0" BUSNAME="dlmb_port" BUSSTD="XIL" IS_INTCONN="TRUE" NAME="PORTB"/>
      <PORT DIR="I" NAME="BRAM_Rst_A" SIGNAME="__DEF__"/>
      <PORT DIR="I" NAME="BRAM_Clk_A" SIGIS="CLK" SIGNAME="__DEF__"/>
      <PORT DIR="I" NAME="BRAM_EN_A" SIGNAME="__DEF__"/>
      <PORT DIR="I" NAME="BRAM_WEN_A" SIGNAME="__DEF__"/>
      <PORT DIR="I" NAME="BRAM_Addr_A" SIGNAME="__DEF__"/>
      <PORT DIR="O" NAME="BRAM_Din_A" SIGNAME="__DEF__"/>
      <PORT DIR="I" NAME="BRAM_Dout_A" SIGNAME="__DEF__"/>
      <PORT DIR="I" NAME="BRAM_Rst_B" SIGNAME="__DEF__"/>
      <PORT DIR="I" NAME="BRAM_Clk_B" SIGIS="CLK" SIGNAME="__DEF__"/>
      <PORT DIR="I" NAME="BRAM_EN_B" SIGNAME="__DEF__"/>
      <PORT DIR="I" NAME="BRAM_WEN_B" SIGNAME="__DEF__"/>
      <PORT DIR="I" NAME="BRAM_Addr_B" SIGNAME="__DEF__"/>
      <PORT DIR="O" NAME="BRAM_Din_B" SIGNAME="__DEF__"/>
      <PORT DIR="I" NAME="BRAM_Dout_B" SIGNAME="__DEF__"/>
    </MODULE>
    <MODULE BUSINDEX="0" BUSSTD="OPB" DOC_IP="f:/EDK/hw/XilinxProcessorIPLib/pcores/opb_v20_v1_10_c/doc/opb_v20.pdf" HWVERSION="1.10.c" INSTANCE="mb_opb" IPTYPE="BUS" IS_PLACED="TRUE" MODCLASS="BUS" MODTYPE="opb_v20">
      <DESCRIPTION TYPE="SHORT">On-chip Peripheral Bus (OPB) 2.0</DESCRIPTION>
      <DESCRIPTION TYPE="LONG">OPB_V20 On-Chip Peripheral Bus V2.0 with OPB Arbiter (OPB_V20)</DESCRIPTION>
      <PARAMETER NAME="C_BASEADDR" VALUE="0xFFFFFFFF"/>
      <PARAMETER NAME="C_HIGHADDR" VALUE="0x00000000"/>
      <PARAMETER NAME="C_OPB_AWIDTH" VALUE="32"/>
      <PARAMETER NAME="C_OPB_DWIDTH" VALUE="32"/>
      <PARAMETER NAME="C_NUM_MASTERS" VALUE="4"/>
      <PARAMETER NAME="C_NUM_SLAVES" VALUE="4"/>
      <PARAMETER NAME="C_USE_LUT_OR" VALUE="1"/>
      <PARAMETER NAME="C_EXT_RESET_HIGH" VALUE="1"/>
      <PARAMETER NAME="C_DYNAM_PRIORITY" VALUE="0"/>
      <PARAMETER NAME="C_PARK" VALUE="0"/>
      <PARAMETER NAME="C_PROC_INTRFCE" VALUE="0"/>
      <PARAMETER NAME="C_REG_GRANTS" VALUE="1"/>
      <PARAMETER NAME="C_DEV_BLK_ID" VALUE="0"/>
      <PARAMETER NAME="C_DEV_MIR_ENABLE" VALUE="0"/>
      <PORT DIR="I" INMHS="TRUE" NAME="SYS_Rst" SIGNAME="sys_rst_s"/>
      <PORT DIR="I" INMHS="TRUE" NAME="OPB_Clk" SIGIS="CLK" SIGNAME="sys_clk_s"/>
      <PORT DIR="O" NAME="OPB_Rst" SIGNAME="__DEF__"/>
      <PORT DIR="I" NAME="Debug_SYS_Rst" SIGNAME="__DEF__"/>
      <PORT DIR="I" NAME="WDT_Rst" SIGNAME="__DEF__"/>
      <PORT DIR="I" NAME="M_ABus" SIGNAME="__DEF__"/>
      <PORT DIR="I" NAME="M_BE" SIGNAME="__DEF__"/>
      <PORT DIR="I" NAME="M_beXfer" SIGNAME="__DEF__"/>
      <PORT DIR="I" NAME="M_busLock" SIGNAME="__DEF__"/>
      <PORT DIR="I" NAME="M_DBus" SIGNAME="__DEF__"/>
      <PORT DIR="I" NAME="M_DBusEn" SIGNAME="__DEF__"/>
      <PORT DIR="I" NAME="M_DBusEn32_63" SIGNAME="__DEF__"/>
      <PORT DIR="I" NAME="M_dwXfer" SIGNAME="__DEF__"/>
      <PORT DIR="I" NAME="M_fwXfer" SIGNAME="__DEF__"/>
      <PORT DIR="I" NAME="M_hwXfer" SIGNAME="__DEF__"/>
      <PORT DIR="I" NAME="M_request" SIGNAME="__DEF__"/>
      <PORT DIR="I" NAME="M_RNW" SIGNAME="__DEF__"/>
      <PORT DIR="I" NAME="M_select" SIGNAME="__DEF__"/>
      <PORT DIR="I" NAME="M_seqAddr" SIGNAME="__DEF__"/>
      <PORT DIR="I" NAME="Sl_beAck" SIGNAME="__DEF__"/>
      <PORT DIR="I" NAME="Sl_DBus" SIGNAME="__DEF__"/>
      <PORT DIR="I" NAME="Sl_DBusEn" SIGNAME="__DEF__"/>
      <PORT DIR="I" NAME="Sl_DBusEn32_63" SIGNAME="__DEF__"/>
      <PORT DIR="I" NAME="Sl_errAck" SIGNAME="__DEF__"/>
      <PORT DIR="I" NAME="Sl_dwAck" SIGNAME="__DEF__"/>
      <PORT DIR="I" NAME="Sl_fwAck" SIGNAME="__DEF__"/>
      <PORT DIR="I" NAME="Sl_hwAck" SIGNAME="__DEF__"/>
      <PORT DIR="I" NAME="Sl_retry" SIGNAME="__DEF__"/>
      <PORT DIR="I" NAME="Sl_toutSup" SIGNAME="__DEF__"/>
      <PORT DIR="I" NAME="Sl_xferAck" SIGNAME="__DEF__"/>
      <PORT DIR="O" NAME="OPB_MRequest" SIGNAME="__DEF__"/>
      <PORT DIR="O" NAME="OPB_ABus" SIGNAME="__DEF__"/>
      <PORT DIR="O" NAME="OPB_BE" SIGNAME="__DEF__"/>
      <PORT DIR="O" NAME="OPB_beXfer" SIGNAME="__DEF__"/>
      <PORT DIR="O" NAME="OPB_beAck" SIGNAME="__DEF__"/>
      <PORT DIR="O" NAME="OPB_busLock" SIGNAME="__DEF__"/>
      <PORT DIR="O" NAME="OPB_rdDBus" SIGNAME="__DEF__"/>
      <PORT DIR="O" NAME="OPB_wrDBus" SIGNAME="__DEF__"/>
      <PORT DIR="O" NAME="OPB_DBus" SIGNAME="__DEF__"/>
      <PORT DIR="O" NAME="OPB_errAck" SIGNAME="__DEF__"/>
      <PORT DIR="O" NAME="OPB_dwAck" SIGNAME="__DEF__"/>
      <PORT DIR="O" NAME="OPB_dwXfer" SIGNAME="__DEF__"/>
      <PORT DIR="O" NAME="OPB_fwAck" SIGNAME="__DEF__"/>
      <PORT DIR="O" NAME="OPB_fwXfer" SIGNAME="__DEF__"/>
      <PORT DIR="O" NAME="OPB_hwAck" SIGNAME="__DEF__"/>
      <PORT DIR="O" NAME="OPB_hwXfer" SIGNAME="__DEF__"/>
      <PORT DIR="O" NAME="OPB_MGrant" SIGNAME="__DEF__"/>
      <PORT DIR="O" NAME="OPB_pendReq" SIGNAME="__DEF__"/>
      <PORT DIR="O" NAME="OPB_retry" SIGNAME="__DEF__"/>
      <PORT DIR="O" NAME="OPB_RNW" SIGNAME="__DEF__"/>
      <PORT DIR="O" NAME="OPB_select" SIGNAME="__DEF__"/>
      <PORT DIR="O" NAME="OPB_seqAddr" SIGNAME="__DEF__"/>
      <PORT DIR="O" NAME="OPB_timeout" SIGNAME="__DEF__"/>
      <PORT DIR="O" NAME="OPB_toutSup" SIGNAME="__DEF__"/>
      <PORT DIR="O" NAME="OPB_xferAck" SIGNAME="__DEF__"/>
    </MODULE>
    <MODULE DOC_DRIVER="f:/EDK/sw/XilinxProcessorIPLib/drivers/gpio_v2_01_a/doc/html/api/index.html" DOC_IP="f:/EDK/hw/XilinxProcessorIPLib/pcores/opb_gpio_v3_01_b/doc/opb_gpio.pdf" GROUP="B" HWVERSION="3.01.b" INSTANCE="LEDs_8Bit" IPTYPE="PERIPHERAL" IS_PLACED="TRUE" MODCLASS="PERIPHERAL" MODTYPE="opb_gpio">
      <DESCRIPTION TYPE="SHORT">OPB General Purpose IO</DESCRIPTION>
      <DESCRIPTION TYPE="LONG">General Purpose Input/Output (GPIO) core for the On-Chip Peripheral Bus (OPB) bus.</DESCRIPTION>
      <PARAMETER CHANGEDBY="USER" NAME="C_BASEADDR" VALUE="0x40020000"/>
      <PARAMETER CHANGEDBY="USER" NAME="C_HIGHADDR" VALUE="0x4002ffff"/>
      <PARAMETER NAME="C_USER_ID_CODE" VALUE="3"/>
      <PARAMETER NAME="C_OPB_AWIDTH" VALUE="32"/>
      <PARAMETER NAME="C_OPB_DWIDTH" VALUE="32"/>
      <PARAMETER NAME="C_FAMILY" VALUE="virtex2"/>
      <PARAMETER CHANGEDBY="USER" NAME="C_GPIO_WIDTH" VALUE="8"/>
      <PARAMETER NAME="C_ALL_INPUTS" VALUE="0"/>
      <PARAMETER NAME="C_INTERRUPT_PRESENT" VALUE="0"/>
      <PARAMETER CHANGEDBY="USER" NAME="C_IS_BIDIR" VALUE="0"/>
      <PARAMETER NAME="C_DOUT_DEFAULT" VALUE="0x00000000"/>
      <PARAMETER NAME="C_TRI_DEFAULT" VALUE="0xffffffff"/>
      <PARAMETER NAME="C_IS_DUAL" VALUE="0"/>
      <PARAMETER NAME="C_ALL_INPUTS_2" VALUE="0"/>
      <PARAMETER NAME="C_IS_BIDIR_2" VALUE="1"/>
      <PARAMETER NAME="C_DOUT_DEFAULT_2" VALUE="0x00000000"/>
      <PARAMETER NAME="C_TRI_DEFAULT_2" VALUE="0xffffffff"/>
      <BUSINTERFACE BIFRANK="SLAVE" BUSNAME="mb_opb" BUSSTD="OPB" NAME="SOPB"/>
      <PORT DIR="O" INMHS="TRUE" NAME="GPIO_d_out" SIGNAME="fpga_0_LEDs_8Bit_GPIO_d_out"/>
      <PORT DIR="I" NAME="OPB_ABus" SIGNAME="__DEF__"/>
      <PORT DIR="I" NAME="OPB_BE" SIGNAME="__DEF__"/>
      <PORT DIR="I" NAME="OPB_Clk" SIGIS="Clk" SIGNAME="__DEF__"/>
      <PORT DIR="I" NAME="OPB_DBus" SIGNAME="__DEF__"/>
      <PORT DIR="I" NAME="OPB_RNW" SIGNAME="__DEF__"/>
      <PORT DIR="I" NAME="OPB_Rst" SIGIS="Rst" SIGNAME="__DEF__"/>
      <PORT DIR="I" NAME="OPB_select" SIGNAME="__DEF__"/>
      <PORT DIR="I" NAME="OPB_seqAddr" SIGNAME="__DEF__"/>
      <PORT DIR="O" NAME="Sln_DBus" SIGNAME="__DEF__"/>
      <PORT DIR="O" NAME="Sln_errAck" SIGNAME="__DEF__"/>
      <PORT DIR="O" NAME="Sln_retry" SIGNAME="__DEF__"/>
      <PORT DIR="O" NAME="Sln_toutSup" SIGNAME="__DEF__"/>
      <PORT DIR="O" NAME="Sln_xferAck" SIGNAME="__DEF__"/>
      <PORT DIR="O" NAME="IP2INTC_Irpt" SIGIS="INTERRUPT" SIGNAME="__NOC__"/>
      <PORT DIR="IO" NAME="GPIO_IO" SIGNAME="__NOC__"/>
      <PORT DIR="I" NAME="GPIO_in" SIGNAME="__NOC__"/>
      <PORT DIR="O" NAME="GPIO_t_out" SIGNAME="__NOC__"/>
      <PORT DIR="IO" NAME="GPIO2_IO" SIGNAME="__NOC__"/>
      <PORT DIR="I" NAME="GPIO2_in" SIGNAME="__NOC__"/>
      <PORT DIR="O" NAME="GPIO2_d_out" SIGNAME="__NOC__"/>
      <PORT DIR="O" NAME="GPIO2_t_out" SIGNAME="__NOC__"/>
      <PORT DIR="I" NAME="GPIO_IO_I" SIGNAME="__NOC__"/>
      <PORT DIR="O" NAME="GPIO_IO_O" SIGNAME="__NOC__"/>
      <PORT DIR="O" NAME="GPIO_IO_T" SIGNAME="__NOC__"/>
      <PORT DIR="I" NAME="GPIO2_IO_I" SIGNAME="__NOC__"/>
      <PORT DIR="O" NAME="GPIO2_IO_O" SIGNAME="__NOC__"/>
      <PORT DIR="O" NAME="GPIO2_IO_T" SIGNAME="__NOC__"/>
    </MODULE>
    <MODULE DOC_DRIVER="f:/EDK/sw/XilinxProcessorIPLib/drivers/gpio_v2_01_a/doc/html/api/index.html" DOC_IP="f:/EDK/hw/XilinxProcessorIPLib/pcores/opb_gpio_v3_01_b/doc/opb_gpio.pdf" GROUP="A" HWVERSION="3.01.b" INSTANCE="DIP_Switches_4Bit" IPTYPE="PERIPHERAL" IS_PLACED="TRUE" MODCLASS="PERIPHERAL" MODTYPE="opb_gpio">
      <DESCRIPTION TYPE="SHORT">OPB General Purpose IO</DESCRIPTION>
      <DESCRIPTION TYPE="LONG">General Purpose Input/Output (GPIO) core for the On-Chip Peripheral Bus (OPB) bus.</DESCRIPTION>
      <PARAMETER CHANGEDBY="USER" NAME="C_BASEADDR" VALUE="0x40000000"/>
      <PARAMETER CHANGEDBY="USER" NAME="C_HIGHADDR" VALUE="0x4000ffff"/>
      <PARAMETER NAME="C_USER_ID_CODE" VALUE="3"/>
      <PARAMETER NAME="C_OPB_AWIDTH" VALUE="32"/>
      <PARAMETER NAME="C_OPB_DWIDTH" VALUE="32"/>
      <PARAMETER NAME="C_FAMILY" VALUE="virtex2"/>
      <PARAMETER CHANGEDBY="USER" NAME="C_GPIO_WIDTH" VALUE="4"/>
      <PARAMETER CHANGEDBY="USER" NAME="C_ALL_INPUTS" VALUE="1"/>
      <PARAMETER NAME="C_INTERRUPT_PRESENT" VALUE="0"/>
      <PARAMETER CHANGEDBY="USER" NAME="C_IS_BIDIR" VALUE="0"/>
      <PARAMETER NAME="C_DOUT_DEFAULT" VALUE="0x00000000"/>
      <PARAMETER NAME="C_TRI_DEFAULT" VALUE="0xffffffff"/>
      <PARAMETER NAME="C_IS_DUAL" VALUE="0"/>
      <PARAMETER NAME="C_ALL_INPUTS_2" VALUE="0"/>
      <PARAMETER NAME="C_IS_BIDIR_2" VALUE="1"/>
      <PARAMETER NAME="C_DOUT_DEFAULT_2" VALUE="0x00000000"/>
      <PARAMETER NAME="C_TRI_DEFAULT_2" VALUE="0xffffffff"/>
      <BUSINTERFACE BIFRANK="SLAVE" BUSNAME="mb_opb" BUSSTD="OPB" NAME="SOPB"/>
      <PORT DIR="I" INMHS="TRUE" NAME="GPIO_in" SIGNAME="fpga_0_DIP_Switches_4Bit_GPIO_in"/>
      <PORT DIR="I" NAME="OPB_ABus" SIGNAME="__DEF__"/>
      <PORT DIR="I" NAME="OPB_BE" SIGNAME="__DEF__"/>
      <PORT DIR="I" NAME="OPB_Clk" SIGIS="Clk" SIGNAME="__DEF__"/>
      <PORT DIR="I" NAME="OPB_DBus" SIGNAME="__DEF__"/>
      <PORT DIR="I" NAME="OPB_RNW" SIGNAME="__DEF__"/>
      <PORT DIR="I" NAME="OPB_Rst" SIGIS="Rst" SIGNAME="__DEF__"/>
      <PORT DIR="I" NAME="OPB_select" SIGNAME="__DEF__"/>
      <PORT DIR="I" NAME="OPB_seqAddr" SIGNAME="__DEF__"/>
      <PORT DIR="O" NAME="Sln_DBus" SIGNAME="__DEF__"/>
      <PORT DIR="O" NAME="Sln_errAck" SIGNAME="__DEF__"/>
      <PORT DIR="O" NAME="Sln_retry" SIGNAME="__DEF__"/>
      <PORT DIR="O" NAME="Sln_toutSup" SIGNAME="__DEF__"/>
      <PORT DIR="O" NAME="Sln_xferAck" SIGNAME="__DEF__"/>
      <PORT DIR="O" NAME="IP2INTC_Irpt" SIGIS="INTERRUPT" SIGNAME="__NOC__"/>
      <PORT DIR="IO" NAME="GPIO_IO" SIGNAME="__NOC__"/>
      <PORT DIR="O" NAME="GPIO_d_out" SIGNAME="__NOC__"/>
      <PORT DIR="O" NAME="GPIO_t_out" SIGNAME="__NOC__"/>
      <PORT DIR="IO" NAME="GPIO2_IO" SIGNAME="__NOC__"/>
      <PORT DIR="I" NAME="GPIO2_in" SIGNAME="__NOC__"/>
      <PORT DIR="O" NAME="GPIO2_d_out" SIGNAME="__NOC__"/>
      <PORT DIR="O" NAME="GPIO2_t_out" SIGNAME="__NOC__"/>
      <PORT DIR="I" NAME="GPIO_IO_I" SIGNAME="__NOC__"/>
      <PORT DIR="O" NAME="GPIO_IO_O" SIGNAME="__NOC__"/>
      <PORT DIR="O" NAME="GPIO_IO_T" SIGNAME="__NOC__"/>
      <PORT DIR="I" NAME="GPIO2_IO_I" SIGNAME="__NOC__"/>
      <PORT DIR="O" NAME="GPIO2_IO_O" SIGNAME="__NOC__"/>
      <PORT DIR="O" NAME="GPIO2_IO_T" SIGNAME="__NOC__"/>
    </MODULE>
    <MODULE DOC_DRIVER="f:/EDK/sw/XilinxProcessorIPLib/drivers/generic_v1_00_a/doc/html/api/index.html" DOC_IP="f:/EDK/hw/XilinxProcessorIPLib/pcores/dcm_module_v1_00_a/doc/dcm_module.pdf" GROUP="C" HWVERSION="1.00.a" INSTANCE="dcm_0" IPTYPE="PERIPHERAL" MODCLASS="IP" MODTYPE="dcm_module">
      <DESCRIPTION TYPE="SHORT">Digital Clock Manager (DCM)</DESCRIPTION>
      <DESCRIPTION TYPE="LONG">The digital clock manager module is a wrapper around the DCM primitive which allows it to be used in the EDK tool suite.</DESCRIPTION>
      <PARAMETER NAME="C_DFS_FREQUENCY_MODE" VALUE="LOW"/>
      <PARAMETER NAME="C_DLL_FREQUENCY_MODE" VALUE="LOW"/>
      <PARAMETER NAME="C_DUTY_CYCLE_CORRECTION" VALUE="TRUE"/>
      <PARAMETER NAME="C_CLKIN_DIVIDE_BY_2" VALUE="FALSE"/>
      <PARAMETER NAME="C_CLK_FEEDBACK" VALUE="1X"/>
      <PARAMETER NAME="C_CLKOUT_PHASE_SHIFT" VALUE="NONE"/>
      <PARAMETER NAME="C_DSS_MODE" VALUE="NONE"/>
      <PARAMETER NAME="C_STARTUP_WAIT" VALUE="FALSE"/>
      <PARAMETER NAME="C_PHASE_SHIFT" VALUE="0"/>
      <PARAMETER NAME="C_CLKFX_MULTIPLY" VALUE="4"/>
      <PARAMETER NAME="C_CLKFX_DIVIDE" VALUE="1"/>
      <PARAMETER NAME="C_CLKDV_DIVIDE" VALUE="2.0"/>
      <PARAMETER CHANGEDBY="USER" NAME="C_CLKIN_PERIOD" VALUE="20.000000"/>
      <PARAMETER NAME="C_DESKEW_ADJUST" VALUE="SYSTEM_SYNCHRONOUS"/>
      <PARAMETER NAME="C_CLKIN_BUF" VALUE="FALSE"/>
      <PARAMETER NAME="C_CLKFB_BUF" VALUE="FALSE"/>
      <PARAMETER CHANGEDBY="USER" NAME="C_CLK0_BUF" VALUE="TRUE"/>
      <PARAMETER NAME="C_CLK90_BUF" VALUE="FALSE"/>
      <PARAMETER NAME="C_CLK180_BUF" VALUE="FALSE"/>
      <PARAMETER NAME="C_CLK270_BUF" VALUE="FALSE"/>
      <PARAMETER NAME="C_CLKDV_BUF" VALUE="FALSE"/>
      <PARAMETER NAME="C_CLK2X_BUF" VALUE="FALSE"/>
      <PARAMETER NAME="C_CLK2X180_BUF" VALUE="FALSE"/>
      <PARAMETER NAME="C_CLKFX_BUF" VALUE="FALSE"/>
      <PARAMETER NAME="C_CLKFX180_BUF" VALUE="FALSE"/>
      <PARAMETER NAME="C_EXT_RESET_HIGH" VALUE="1"/>
      <PARAMETER NAME="C_FAMILY" VALUE="virtex2"/>
      <PORT DIR="I" INMHS="TRUE" NAME="CLKIN" SIGIS="CLK" SIGNAME="dcm_clk_s"/>
      <PORT DIR="O" INMHS="TRUE" NAME="CLK0" SIGIS="CLK" SIGNAME="sys_clk_s"/>
      <PORT DIR="I" INMHS="TRUE" NAME="CLKFB" SIGNAME="sys_clk_s"/>
      <PORT DIR="I" INMHS="TRUE" NAME="RST" SIGNAME="net_gnd"/>
      <PORT DIR="O" INMHS="TRUE" NAME="LOCKED" SIGNAME="dcm_0_lock"/>
      <PORT DIR="I" NAME="PSEN" SIGNAME="__NOC__"/>
      <PORT DIR="I" NAME="PSINCDEC" SIGNAME="__NOC__"/>
      <PORT DIR="I" NAME="PSCLK" SIGNAME="__NOC__"/>
      <PORT DIR="I" NAME="DSSEN" SIGNAME="__NOC__"/>
      <PORT DIR="O" NAME="CLK90" SIGIS="CLK" SIGNAME="__NOC__"/>
      <PORT DIR="O" NAME="CLK180" SIGIS="CLK" SIGNAME="__NOC__"/>
      <PORT DIR="O" NAME="CLK270" SIGIS="CLK" SIGNAME="__NOC__"/>
      <PORT DIR="O" NAME="CLKDV" SIGIS="CLK" SIGNAME="__NOC__"/>
      <PORT DIR="O" NAME="CLK2X" SIGIS="CLK" SIGNAME="__NOC__"/>
      <PORT DIR="O" NAME="CLK2X180" SIGIS="CLK" SIGNAME="__NOC__"/>
      <PORT DIR="O" NAME="CLKFX" SIGIS="CLK" SIGNAME="__NOC__"/>
      <PORT DIR="O" NAME="CLKFX180" SIGIS="CLK" SIGNAME="__NOC__"/>
      <PORT DIR="O" NAME="STATUS" SIGNAME="__NOC__"/>
      <PORT DIR="O" NAME="PSDONE" SIGNAME="__NOC__"/>
    </MODULE>
  </MODULES>

  <EXTERNALPORTS>
    <PORT DIR="O" ENDIAN="LITTLE" GROUP="B" INDEX="2" LSB="0" MSB="7" NAME="fpga_0_LEDs_8Bit_GPIO_d_out_pin" SIGNAME="fpga_0_LEDs_8Bit_GPIO_d_out"/>
    <PORT DIR="I" ENDIAN="LITTLE" GROUP="A" INDEX="1" LSB="0" MSB="3" NAME="fpga_0_DIP_Switches_4Bit_GPIO_in_pin" SIGNAME="fpga_0_DIP_Switches_4Bit_GPIO_in"/>
    <PORT DIR="I" GROUP="C" INDEX="3" NAME="sys_clk_pin" SIGIS="CLK" SIGNAME="dcm_clk_s"/>
    <PORT DIR="I" GROUP="GLB" INDEX="0" NAME="sys_rst_pin" SIGIS="RST" SIGNAME="sys_rst_s"/>
  </EXTERNALPORTS>

  <BLKDSHAPES STACK_HORIZ_WIDTH="1">
    <PROCSHAPES>
      <MODULE BIFS_H="2" BIFS_W="2" INSTANCE="microblaze_0" IS_ABVSBS="TRUE" SHAPE_VERTI_INDEX="1" STACK_HORIZ_INDEX="0"/>
    </PROCSHAPES>
    <IPBUCKET MODS_H="1" MODS_W="1">
      <MODULE INSTANCE="dcm_0" IS_PLACED="TRUE" MODTYPE="dcm_module"/>
    </IPBUCKET>
    <SBSSHAPES>
      <MODULE INSTANCE="mb_opb"/>
    </SBSSHAPES>
    <SBSBUCKETS>
      <SBSBUCKET BUSINDEX="0" BUSNAME="mb_opb" BUSSTD="OPB" IS_BLWSBS="TRUE" MODS_H="1" MODS_W="2" SHAPE_VERTI_INDEX="2" STACK_HORIZ_INDEX="0">
        <MODULE INSTANCE="LEDs_8Bit" MODTYPE="opb_gpio"/>
        <MODULE INSTANCE="DIP_Switches_4Bit" MODTYPE="opb_gpio"/>
      </SBSBUCKET>
    </SBSBUCKETS>
    <P2PSHAPES>
      <MODULE INSTANCE="ilmb"/>
      <MODULE INSTANCE="dlmb"/>
    </P2PSHAPES>
    <CMPLXSHAPES>
      <CMPLXSHAPE IS_ABVSBS="TRUE" MODCLASS="MEMORY_UNIT" MODS_H="2" MODS_W="2" SHAPE_ID="0" SHAPE_VERTI_INDEX="0" STACK_HORIZ_INDEX="0">
        <MODULE BIFS_H="1" BIFS_W="2" INSTANCE="ilmb_cntlr" MODCLASS="MEMORY_CNTLR" ORIENTED="EAST"/>
        <MODULE BIFS_H="1" BIFS_W="2" INSTANCE="dlmb_cntlr" MODCLASS="MEMORY_CNTLR" ORIENTED="WEST"/>
        <MODULE BIFS_H="1" BIFS_W="2" INSTANCE="lmb_bram" MODCLASS="MEMORY"/>
      </CMPLXSHAPE>
    </CMPLXSHAPES>
    <BCLANESPACES>
      <BCLANESPACE BUSLANES_W="4" EAST="0">
        <BUSCONNLANE BUSLANE_X="2" BUSNAME="dlmb" BUSSTD="LMB" IS_MEMCONN="TRUE" ORIENTED="EAST" STACK_HORIZ_INDEX="0">
          <BUSCONN BIF_Y="0" BUSINTERFACE="DLMB" INSTANCE="microblaze_0" IS_PROCONN="TRUE"/>
          <BUSCONN BUSINTERFACE="SLMB" BUSSTD="LMB" INSTANCE="dlmb_cntlr"/>
        </BUSCONNLANE>
        <BUSCONNLANE BUSLANE_X="2" BUSNAME="mb_opb" BUSSTD="OPB" IS_SBSCONN="TRUE" ORIENTED="EAST" STACK_HORIZ_INDEX="0">
          <BUSCONN BIF_Y="1" BUSINTERFACE="DOPB" INSTANCE="microblaze_0" IS_PROCONN="TRUE"/>
        </BUSCONNLANE>
        <BUSCONNLANE BUSLANE_X="1" BUSNAME="mb_opb" BUSSTD="OPB" IS_BKTCONN="TRUE" ORIENTED="EAST" STACK_HORIZ_INDEX="0">
          <BUSCONN BIFRANK="SLAVE" BUSINTERFACE="SOPB"/>
        </BUSCONNLANE>
      </BCLANESPACE>
      <BCLANESPACE BUSLANES_W="3" WEST="0">
        <BUSCONNLANE BUSLANE_X="1" BUSNAME="ilmb" BUSSTD="LMB" IS_MEMCONN="TRUE" ORIENTED="WEST" STACK_HORIZ_INDEX="0">
          <BUSCONN BIF_Y="0" BUSINTERFACE="ILMB" INSTANCE="microblaze_0" IS_PROCONN="TRUE"/>
          <BUSCONN BUSINTERFACE="SLMB" BUSSTD="LMB" INSTANCE="ilmb_cntlr"/>
        </BUSCONNLANE>
        <BUSCONNLANE BUSLANE_X="1" BUSNAME="mb_opb" BUSSTD="OPB" IS_SBSCONN="TRUE" ORIENTED="WEST" STACK_HORIZ_INDEX="0">
          <BUSCONN BIF_Y="1" BUSINTERFACE="IOPB" INSTANCE="microblaze_0" IS_PROCONN="TRUE"/>
        </BUSCONNLANE>
      </BCLANESPACE>
    </BCLANESPACES>
  </BLKDSHAPES>

</EDKSYSTEM>